{
  "project_info": {
    "project_number": "529301459679",
    "project_id": "women-bda91",
    "storage_bucket": "women-bda91.appspot.com"
  },
  "client": [
    {
      "client_info": {
        "mobilesdk_app_id": "1:529301459679:android:b4f3abe24a99b494a08f6a",
        "android_client_info": {
          "package_name": "com.rehman.womansecuritysystem"
        }
      },
      "oauth_client": [],
      "api_key": [
        {
          "current_key": "AIzaSyDcO3hRrYLI_wloAGS3KGn5WYHB6dGinIk"
        }
      ],
      "services": {
        "appinvite_service": {
          "other_platform_oauth_client": []
        }
      }
    }
  ],
  "configuration_version": "1"
}